hg-wiki
hgwiki.py
setup.py
hg_wiki.egg-info/PKG-INFO
hg_wiki.egg-info/SOURCES.txt
hg_wiki.egg-info/dependency_links.txt
hg_wiki.egg-info/requires.txt
hg_wiki.egg-info/top_level.txt