Metadata-Version: 1.1
Name: hg-wiki
Version: 1.0
Summary: mercurial based wiki
Home-page: http://bitbucket.org/javisantana/hg-wiki/
Author: javier santana
Author-email: jsantfer@gmail.com
License: UNKNOWN
Platform: UNKNOWN
Requires: creoleparser
Requires: SQLAlchemy
Requires: juno
